[
  {
    "title": "My Project",
    "slug": "project-1",
    "url": "https://example.com",
    "image": "../images/projects/project1.jpg",
    "descriprion": "Deserunt cupidatat quis quis dolor sint culpa ad cillum tempor eu consequat dolor. Sint consectetur enim cillum ullamco excepteur excepteur dolore cillum quis. Velit sit qui ut labore ullamco nostrud id ad elit ea aliquip. Enim aute proident incididunt in proident ullamco anim. Tempor cillum labore voluptate voluptate dolor mollit pariatur mollit consectetur enim minim est laborum. Aliqua elit velit labore culpa pariatur nisi laborum excepteur minim anim. Laboris eu do minim anim."
  },
  {
    "title": "Another Project",
    "slug": "project-2",
    "url": "https://example.org",
    "image": "../images/projects/project2.jpg",
    "descriprion": "Deserunt cupidatat quis quis dolor sint culpa ad cillum tempor eu consequat dolor. Sint consectetur enim cillum ullamco excepteur excepteur dolore cillum quis. Velit sit qui ut labore ullamco nostrud id ad elit ea aliquip. Enim aute proident incididunt in proident ullamco anim. Tempor cillum labore voluptate voluptate dolor mollit pariatur mollit consectetur enim minim est laborum. Aliqua elit velit labore culpa pariatur nisi laborum excepteur minim anim. Laboris eu do minim anim."
  }
]
